pydynotree.cpython-311-x86_64-linux-gnu.so
dynotree-0.0.5.dist-info/WHEEL
dynotree-0.0.5.dist-info/RECORD
dynotree-0.0.5.dist-info/METADATA
dynotree-0.0.5.dist-info/top_level.txt
dynotree-0.0.5.dist-info/LICENSE.txt
