Metadata-Version: 2.1
Name: dynotree
Version: 0.0.5
Summary: Dynotree - Dynamic Kd tree
Author: Joaquim Ortiz-Haro
Author-email: quimortiz21@gmail.com
Project-URL: Github, https://github.com/quimortiz/dynotree/
Requires-Python: >=3.6
License-File: LICENSE.txt
Provides-Extra: test
Requires-Dist: pytest >=6.0 ; extra == 'test'
